tscv/__init__.py
tscv/_split.py
tscv/tests/__init__.py
tscv/tests/test_split.py
tscv-0.1.3.dist-info/LICENSE
tscv-0.1.3.dist-info/METADATA
tscv-0.1.3.dist-info/WHEEL
tscv-0.1.3.dist-info/top_level.txt
tscv-0.1.3.dist-info/RECORD
