Metadata-Version: 2.1
Name: tscv
Version: 0.1.3
Summary: Time series cross-validation
Home-page: https://github.com/WenjieZ/TSCV
Author: Wenjie Zheng
Author-email: work@zhengwenjie.net
License: new BSD
Keywords: model selection,hyperparameter optimization,backtesting
Classifier: Intended Audience :: Science/Research
Classifier: Intended Audience :: Developers
Classifier: License :: OSI Approved :: BSD License
Classifier: Programming Language :: Python
Classifier: Topic :: Software Development
Classifier: Topic :: Scientific/Engineering
Classifier: Development Status :: 5 - Production/Stable
Classifier: Operating System :: Microsoft :: Windows
Classifier: Operating System :: POSIX
Classifier: Operating System :: Unix
Classifier: Operating System :: MacOS
Classifier: Programming Language :: Python :: 3
Classifier: Programming Language :: Python :: 3.6
Classifier: Programming Language :: Python :: 3.7
Classifier: Programming Language :: Python :: 3.8
Classifier: Programming Language :: Python :: 3.9
Classifier: Programming Language :: Python :: 3.10
Classifier: Programming Language :: Python :: 3.11
Requires-Python: >=3.6
License-File: LICENSE
Requires-Dist: numpy (>=1.13.3)
Requires-Dist: scikit-learn (>=0.22)
